sysdfiles/__init__.py
sysdfiles/automount_file.py
sysdfiles/conf_file.py
sysdfiles/device_file.py
sysdfiles/hostname_file.py
sysdfiles/hosts_file.py
sysdfiles/ini_file.py
sysdfiles/link_file.py
sysdfiles/machine_id_file.py
sysdfiles/machine_info_file.py
sysdfiles/mount_file.py
sysdfiles/network_file.py
sysdfiles/os_release_file.py
sysdfiles/path_file.py
sysdfiles/scope_file.py
sysdfiles/service_file.py
sysdfiles/slice_file.py
sysdfiles/socket_file.py
sysdfiles/swap_file.py
sysdfiles/target_file.py
sysdfiles/timer_file.py
sysdfiles/unit_file.py
sysdfiles/value_file.py
sysdfiles/vars_file.py
sysdfiles-0.2.0.dist-info/LICENSE.txt
sysdfiles-0.2.0.dist-info/METADATA
sysdfiles-0.2.0.dist-info/WHEEL
sysdfiles-0.2.0.dist-info/top_level.txt
sysdfiles-0.2.0.dist-info/RECORD
