Metadata-Version: 2.1
Name: sysdfiles
Version: 0.2.0
Summary: systemd configuration file access
Home-page: https://github.com/ShawnBaker/sysdfiles
Author: Shawn Baker
Author-email: support@frozen.ca
License: MIT
Project-URL: Documentation, https://github.com/ShawnBaker/sysdfiles/wiki
Project-URL: Source, https://github.com/ShawnBaker/sysdfiles
Keywords: systemd configuration file files automount conf device hostname hosts ini link machine-id machine-info mount network os-release path scope service slice socket swap target timer unit
Platform: UNKNOWN
Classifier: Development Status :: 4 - Beta
Classifier: Intended Audience :: Developers
Classifier: License :: OSI Approved :: MIT License
Classifier: Operating System :: POSIX :: Linux
Classifier: Programming Language :: Python :: 3
Classifier: Programming Language :: Python :: 3.6
Classifier: Topic :: Software Development :: Libraries :: Python Modules
Classifier: Topic :: System :: Operating System
